scabi/__init__.py
scabi/__main__.py
scabi/crawler.py
scabi/utility_cli.py
scabi-1.0.1.dist-info/METADATA
scabi-1.0.1.dist-info/WHEEL
scabi-1.0.1.dist-info/entry_points.txt
scabi-1.0.1.dist-info/top_level.txt
scabi-1.0.1.dist-info/RECORD
