Metadata-Version: 2.1
Name: scabi
Version: 1.0.1
Summary: Implement vulnerabilities scanning on top of package management system like apt, pip, composer...
Home-page: https://github.com/remiflavien1/scabi
Author: shadawck
Author-email: hug211mire@gmail.com
License: MIT
Keywords: security,dependencies,package management
Platform: UNKNOWN
Classifier: License :: OSI Approved :: MIT License
Classifier: Programming Language :: Python :: 3
Classifier: Programming Language :: Python :: 3.7
Classifier: Topic :: Security
Requires-Dist: requests
Requires-Dist: mitrecve
Requires-Dist: getdep
Requires-Dist: docopt
Provides-Extra: test
Requires-Dist: pytest ; extra == 'test'
Requires-Dist: pytest-cov ; extra == 'test'
